amway_eap_migration/__init__.py
amway_eap_migration-0.1.dist-info/METADATA
amway_eap_migration-0.1.dist-info/WHEEL
amway_eap_migration-0.1.dist-info/top_level.txt
amway_eap_migration-0.1.dist-info/RECORD
